drap/__init__.py
drap/automation.py
drap/gui.py
drap/main.py
drap/qt_adjust.py
drap/terminal_interface.py
drap/utils.py
drap/resources/DrapuserGuide_eng.pdf
drap/resources/DrapuserGuide_pt.pdf
drap/resources/name_videos.dat
drap-0.0.4.post15.dist-info/licenses/LICENSE
drap-0.0.4.post15.dist-info/METADATA
drap-0.0.4.post15.dist-info/WHEEL
drap-0.0.4.post15.dist-info/entry_points.txt
drap-0.0.4.post15.dist-info/top_level.txt
drap-0.0.4.post15.dist-info/RECORD
